[{"id":"306aee5c.263202","type":"tab","label":"Flow 1","disabled":false,"info":""},{"id":"2bdae3c7.cb7f0c","type":"http in","z":"306aee5c.263202","name":"beanstalked","url":"/plate","method":"post","upload":true,"swaggerDoc":"","x":190,"y":260,"wires":[["e1d4f87c.d61148","6a6621c3.d8729"]]},{"id":"e7fc937b.89f7d","type":"http response","z":"306aee5c.263202","name":"","statusCode":"","headers":{},"x":770,"y":280,"wires":[]},{"id":"e1d4f87c.d61148","type":"debug","z":"306aee5c.263202","name":"","active":true,"tosidebar":true,"console":false,"tostatus":false,"complete":"false","x":460,"y":180,"wires":[]},{"id":"6a6621c3.d8729","type":"json","z":"306aee5c.263202","name":"","property":"payload","action":"","pretty":true,"x":400,"y":280,"wires":[["714ef777.f2da38"]]},{"id":"714ef777.f2da38","type":"file","z":"306aee5c.263202","name":"json out","filename":"/home/debo/repos/anpr/public/result.json","appendNewline":true,"createDir":true,"overwriteFile":"false","encoding":"none","x":380,"y":460,"wires":[["e7fc937b.89f7d"]]}]